downwards/__init__.py
downwards/__version__.py
downwards-1.3.0.dist-info/LICENSE
downwards-1.3.0.dist-info/METADATA
downwards-1.3.0.dist-info/WHEEL
downwards-1.3.0.dist-info/entry_points.txt
downwards-1.3.0.dist-info/top_level.txt
downwards-1.3.0.dist-info/RECORD
