Metadata-Version: 2.1
Name: downwards
Version: 1.3.0
Summary: downwards lets you read a wikipedia page on command line as a manpage.
Home-page: https://github.com/noqqe/downwards/
Author: Florian Baumann
License: MIT
Project-URL: Source, https://github.com/noqqe/downwards/
Project-URL: Documentation, https://github.com/noqqe/downwards/
Platform: UNKNOWN
Classifier: Development Status :: 5 - Production/Stable
Classifier: Environment :: Web Environment
Classifier: License :: OSI Approved :: MIT License
Classifier: Operating System :: OS Independent
Classifier: Programming Language :: Python
Classifier: Programming Language :: Python :: 3 :: Only
Classifier: Programming Language :: Python :: 3.5
Classifier: Programming Language :: Python :: 3.6
Classifier: Programming Language :: Python :: 3.7
Classifier: Programming Language :: Python :: 3.8
Classifier: Topic :: Games/Entertainment
Classifier: Topic :: Internet :: WWW/HTTP :: Dynamic Content
Requires-Python: >=3.5
Requires-Dist: click
Requires-Dist: wikipedia
Requires-Dist: wikitextparser
Requires-Dist: mako
Requires-Dist: unidecode
